geosketch/__init__.py
geosketch/kmeanspp.py
geosketch/sketch.py
geosketch/utils.py
geosketch-1.3.dist-info/LICENSE
geosketch-1.3.dist-info/METADATA
geosketch-1.3.dist-info/WHEEL
geosketch-1.3.dist-info/top_level.txt
geosketch-1.3.dist-info/RECORD
