Metadata-Version: 2.1
Name: geosketch
Version: 1.3
Summary: Geometry-preserving random sampling
Home-page: https://github.com/brianhie/geosketch
Download-URL: https://github.com/brianhie/geosketch/archive/v1.3.tar.gz
Author: Brian Hie
Author-email: brianhie@mit.edu
License: MIT
License-File: LICENSE
Requires-Dist: fbpca >=1.0
Requires-Dist: numpy >=1.12.0
Requires-Dist: scikit-learn >=0.24
